giayap/__init__.py
giayap/__version__.py
giayap/giayap.pydd
giayap/index_2_word.json
giayap/model_training.onnx
giayap-0.0.6.dist-info/METADATA
giayap-0.0.6.dist-info/WHEEL
giayap-0.0.6.dist-info/RECORD
