Metadata-Version: 2.3
Name: giayap
Version: 0.0.6
Summary: yap for GIA.
Author: Infstellar
Classifier: License :: OSI Approved :: MIT License
Classifier: Operating System :: OS Independent
Classifier: Programming Language :: Python :: 3
Requires-Python: >=3.7
